test_py_cpp/_core.cpython-39-x86_64-linux-gnu.so
test_py_cpp/__init__.py
test_py_cpp-0.6.0.dist-info/METADATA
test_py_cpp-0.6.0.dist-info/RECORD
test_py_cpp-0.6.0.dist-info/WHEEL
